puregym_attendance.py
puregym_attendance-2.0.dist-info/METADATA
puregym_attendance-2.0.dist-info/WHEEL
puregym_attendance-2.0.dist-info/licenses/LICENSE
puregym_attendance-2.0.dist-info/RECORD
