Metadata-Version: 2.4
Name: puregym_attendance
Version: 2.0
Summary: A python client to query the PureGym mobile API for live gym attendance
License-File: LICENSE
Author: Tom Hollingsworth
Author-email: tom@holli.dev
Requires-Python: >=3.8
Classifier: Programming Language :: Python :: 3
Classifier: Programming Language :: Python :: 3.8
Classifier: Programming Language :: Python :: 3.9
Classifier: Programming Language :: Python :: 3.10
Classifier: Programming Language :: Python :: 3.11
Classifier: Programming Language :: Python :: 3.12
Classifier: Programming Language :: Python :: 3.13
Classifier: Programming Language :: Python :: 3.14
Requires-Dist: requests (>=2.32.4)
Requires-Dist: textdistance (>=4.6.3)
Project-URL: Repository, https://github.com/2t6h/puregym-attendance
